MANIFEST.in
README.rst
setup.py
cachel/__init__.py
cachel/_async_base.py
cachel/base.py
cachel/compat.py
cachel/offload.py
cachel/redis.py
cachel/simple.py
cachel/uwsgi.py
cachel.egg-info/PKG-INFO
cachel.egg-info/SOURCES.txt
cachel.egg-info/dependency_links.txt
cachel.egg-info/not-zip-safe
cachel.egg-info/requires.txt
cachel.egg-info/top_level.txt
cachel/wrappers/__init__.py
cachel/wrappers/async_cache.py
cachel/wrappers/async_fn.py
cachel/wrappers/full_async.py
cachel/wrappers/full_sync.py
cachel/wrappers/gen.py
cachel/wrappers/template.py